image_analyst/cv2/__init__.py
image_analyst/cv2/image.py
image_analyst/cv2/models.py
image_analyst/cv2/utils.py
image_analyst_cv2-0.2.0.dist-info/LICENSE
image_analyst_cv2-0.2.0.dist-info/METADATA
image_analyst_cv2-0.2.0.dist-info/WHEEL
image_analyst_cv2-0.2.0.dist-info/RECORD
