Metadata-Version: 2.1
Name: image-analyst-cv2
Version: 0.2.0
Summary: ImageAnalyst CV2 is an extension to the ImageAnalyst library, providing additional models and functions using cv2.
Home-page: https://github.com/BergLucas/ImageAnalystCV2
Keywords: image,analysis,cv2
Author: Lucas Berg
Author-email: 55436804+BergLucas@users.noreply.github.com
Requires-Python: >=3.9,<4.0
Classifier: Development Status :: 3 - Alpha
Classifier: License :: OSI Approved :: MIT License
Classifier: Programming Language :: Python :: 3
Classifier: Programming Language :: Python :: 3.9
Classifier: Programming Language :: Python :: 3.10
Classifier: Programming Language :: Python :: 3.11
Provides-Extra: cv2
Provides-Extra: cv2-headless
Requires-Dist: image-analyst (>=0.2.0,<0.3.0)
Requires-Dist: numpy (>=1.24.3,<2.0.0)
Requires-Dist: opencv-contrib-python (>=4.8.0.74,<5.0.0.0) ; extra == "cv2"
Requires-Dist: opencv-contrib-python-headless (>=4.8.0.74,<5.0.0.0) ; extra == "cv2-headless"
Project-URL: Repository, https://github.com/BergLucas/ImageAnalystCV2
